AUTHORS.rst
CONTRIBUTING.rst
HISTORY.rst
LICENSE
MANIFEST.in
README.rst
requirements.txt
setup.cfg
setup.py
docs/Makefile
docs/authors.rst
docs/conf.py
docs/contributing.rst
docs/history.rst
docs/index.rst
docs/installation.rst
docs/make.bat
docs/readme.rst
docs/usage.rst
ehour/__init__.py
ehour/api.py
ehour/cli.py
ehour/exceptions.py
ehour/model.py
ehour.egg-info/PKG-INFO
ehour.egg-info/SOURCES.txt
ehour.egg-info/dependency_links.txt
ehour.egg-info/entry_points.txt
ehour.egg-info/not-zip-safe
ehour.egg-info/requires.txt
ehour.egg-info/top_level.txt
tests/test_ehour.py